{
  "league": "NBA + WNBA",
  "generated": "2026-06-07 04:20:21",
  "count": 4,
  "games": [
    {
      "config": null,
      "matchup": "Indiana Fever @ New York Liberty",
      "away": "Indiana Fever",
      "home": "New York Liberty",
      "away_key": "FEV",
      "home_key": "LIB",
      "tip": "8:00 PM",
      "date": "Sat Jun 6, 2026",
      "tip_ms": 1780790400000,
      "league": "WNBA",
      "stage": "live",
      "total": 154.5,
      "pace": "even",
      "proj": 149.6,
      "spread": "LIB +5",
      "ml_away": -300,
      "ml_home": 215
    },
    {
      "config": null,
      "matchup": "Chicago Sky @ Toronto Tempo",
      "away": "Chicago Sky",
      "home": "Toronto Tempo",
      "away_key": "SKY",
      "home_key": "TEM",
      "tip": "3:00 PM",
      "date": "Sun Jun 7, 2026",
      "tip_ms": 1780858800000,
      "league": "WNBA",
      "stage": "pre",
      "total": 173.5,
      "pace": null,
      "proj": null,
      "spread": "TEM -2.5",
      "ml_away": 120,
      "ml_home": -140
    },
    {
      "config": null,
      "matchup": "Portland Fire @ Los Angeles Sparks",
      "away": "Portland Fire",
      "home": "Los Angeles Sparks",
      "away_key": "FIR",
      "home_key": "SPA",
      "tip": "7:00 PM",
      "date": "Sun Jun 7, 2026",
      "tip_ms": 1780873200000,
      "league": "WNBA",
      "stage": "pre",
      "total": 177.5,
      "pace": null,
      "proj": null,
      "spread": "SPA -7.5",
      "ml_away": 240,
      "ml_home": -290
    },
    {
      "config": null,
      "matchup": "San Antonio Spurs @ New York Knicks",
      "away": "San Antonio Spurs",
      "home": "New York Knicks",
      "away_key": "SPU",
      "home_key": "KNI",
      "tip": "8:30 PM",
      "date": "Mon Jun 8, 2026",
      "tip_ms": 1780965000000,
      "league": "NBA",
      "stage": "pre",
      "total": 216.0,
      "pace": null,
      "proj": null,
      "spread": "KNI -2",
      "ml_away": 115,
      "ml_home": -135
    }
  ]
}